README.md
setup.py
bin/epic
bin/epic-blacklist
bin/epic-cluster
bin/epic-count
bin/epic-effective
bin/epic-merge
bin/epic-overlaps
bioepic.egg-info/PKG-INFO
bioepic.egg-info/SOURCES.txt
bioepic.egg-info/dependency_links.txt
bioepic.egg-info/requires.txt
bioepic.egg-info/top_level.txt
epic/__init__.py
epic/version.py
epic/bigwig/__init__.py
epic/bigwig/create_bigwigs.py
epic/blacklist/__init__.py
epic/blacklist/compute_poisson.py
epic/cluster/__init__.py
epic/cluster/cluster.py
epic/config/__init__.py
epic/config/constants.py
epic/config/genomes.py
epic/config/logging_settings.py
epic/matrixes/__init__.py
epic/matrixes/matrixes.py
epic/merge/__init__.py
epic/merge/compute_bed_bins.py
epic/merge/merge.py
epic/merge/merge_helpers.py
epic/run/__init__.py
epic/run/run_epic.py
epic/scripts/__init__.py
epic/scripts/effective_genome_size.py
epic/scripts/genome.snakefile
epic/scripts/chromsizes/ailMel1.chromsizes
epic/scripts/chromsizes/anoCar2.chromsizes
epic/scripts/chromsizes/apiMel1.chromsizes
epic/scripts/chromsizes/aplCal1.chromsizes
epic/scripts/chromsizes/aquChr2.chromsizes
epic/scripts/chromsizes/balAcu1.chromsizes
epic/scripts/chromsizes/braFlo1.chromsizes
epic/scripts/chromsizes/calJac1.chromsizes
epic/scripts/chromsizes/calJac3.chromsizes
epic/scripts/chromsizes/cavPor3.chromsizes
epic/scripts/chromsizes/ce10.chromsizes
epic/scripts/chromsizes/ce11.chromsizes
epic/scripts/chromsizes/cerSim1.chromsizes
epic/scripts/chromsizes/chlSab2.chromsizes
epic/scripts/chromsizes/chrPic1.chromsizes
epic/scripts/chromsizes/danRer10.chromsizes
epic/scripts/chromsizes/danRer3.chromsizes
epic/scripts/chromsizes/danRer4.chromsizes
epic/scripts/chromsizes/danRer5.chromsizes
epic/scripts/chromsizes/danRer6.chromsizes
epic/scripts/chromsizes/danRer7.chromsizes
epic/scripts/chromsizes/dm3.chromsizes
epic/scripts/chromsizes/dm6.chromsizes
epic/scripts/chromsizes/echTel2.chromsizes
epic/scripts/chromsizes/equCab1.chromsizes
epic/scripts/chromsizes/equCab2.chromsizes
epic/scripts/chromsizes/eriEur1.chromsizes
epic/scripts/chromsizes/eriEur2.chromsizes
epic/scripts/chromsizes/fr1.chromsizes
epic/scripts/chromsizes/fr2.chromsizes
