Metadata-Version: 1.1
Name: bioepic
Version: 0.2.12
Summary: Chip-Seq broad peak/domain finder.
Home-page: http://github.com/endrebak/epic
Author: Endre Bakken Stovner
Author-email: endrebak85@gmail.com
License: ['MIT']
Keywords: ChIP-Seq
Platform: UNKNOWN
Classifier: Programming Language :: Python :: 2.7
Classifier: Programming Language :: Python :: 3
Classifier: Development Status :: 4 - Beta
Classifier: Environment :: Other Environment
Classifier: Intended Audience :: Developers
Classifier: Intended Audience :: Science/Research
Classifier: License :: OSI Approved :: GNU General Public License v3 (GPLv3)
Classifier: Operating System :: POSIX :: Linux
Classifier: Operating System :: MacOS :: MacOS X
Classifier: Topic :: Scientific/Engineering
